[{"Služba":"Předbroušení a srovnání skluznice","Standard":"✓","Advanced":"✓","Race":"✓"},{"Služba":"Finishing skluznice (struktura na kameni)","Standard":"✓","Advanced":"✓","Race":"✓"},{"Služba":"Broušení a úhlování spodní hrany","Standard":"✓","Advanced":"✓","Race":"✓"},{"Služba":"Broušení a úhlování boční hrany","Standard":"✓","Advanced":"✓","Race":"✓"},{"Služba":"Odklon spodní hrany 0,3°","Standard":"✓","Advanced":"✓","Race":"✓"},{"Služba":"2x voskování pod UV lampou","Standard":"","Advanced":"✓","Race":"✓"},{"Služba":"Strojní voskování","Standard":"✓","Advanced":"✓","Race":""},{"Služba":"Ruční přeleštění hran","Standard":"","Advanced":"✓","Race":"✓"},{"Služba":"Možnost volby úhlu","Standard":"","Advanced":"","Race":"✓"},{"Služba":"Vyvařování skluznice – zatavení rýh","Standard":"","Advanced":"","Race":"+250 Kč"}]
